pinn_kit/Domain.py
pinn_kit/PINN.py
pinn_kit/__init__.py
pinn_kit-0.1.5.dist-info/METADATA
pinn_kit-0.1.5.dist-info/WHEEL
pinn_kit-0.1.5.dist-info/licenses/LICENSE
pinn_kit-0.1.5.dist-info/RECORD
