Metadata-Version: 2.4
Name: pinn_kit
Version: 0.1.5
Summary: A toolkit for Physics-Informed Neural Networks
Project-URL: Homepage, https://github.com/shivani/PINN-kit
Project-URL: Issues, https://github.com/shivani/PINN-kit/issues
Author-email: Shivani <shivani@example.com>
License-Expression: MIT
License-File: LICENSE
Classifier: Operating System :: OS Independent
Classifier: Programming Language :: Python :: 3
Classifier: Topic :: Scientific/Engineering :: Artificial Intelligence
Classifier: Topic :: Scientific/Engineering :: Physics
Requires-Python: >=3.9
Requires-Dist: matplotlib>=3.5.0
Requires-Dist: numpy>=1.21.0
Requires-Dist: scikit-optimize>=0.9.0
Requires-Dist: torch>=2.0.0
